BOSolver/__init__.py
BOSolver/bosolve.py
BOSolver/cli.py
BOSolver/compute_chg_and_bo.py
BOSolver/utils/__init__.py
BOSolver/utils/chem.py
BOSolver/utils/coord2adj.py
bosolver-0.1.dist-info/licenses/LICENSE
bosolver-0.1.dist-info/METADATA
bosolver-0.1.dist-info/WHEEL
bosolver-0.1.dist-info/entry_points.txt
bosolver-0.1.dist-info/top_level.txt
bosolver-0.1.dist-info/RECORD
