Metadata-Version: 2.4
Name: BOSolver
Version: 0.1
Summary: BOSolver: A Python package for solving Bond Order (and Formal Charge) Assignment based on Integer Linear Programming
Author-email: Jinwon Lee <jinwonlee0310@gmail.com>, Kyunhoon Lee <kyunghoonlee@kaist.ac.kr>
Maintainer-email: Jinwon Lee <jinwonlee0310@gmail.com>
License: MIT
Project-URL: Repository, https://github.com/DOCH-2/BOSolver.git
Classifier: Programming Language :: Python :: 3
Classifier: Operating System :: OS Independent
Requires-Python: >=3.9
License-File: LICENSE
Requires-Dist: rdkit>=2024.09
Requires-Dist: pulp>=2.8.0
Requires-Dist: numpy>=1.26.4
Requires-Dist: scipy>=1.13.1
Dynamic: license-file
